ptrender/__init__.py
ptrender/ptrender.py
ptrender-0.0.3.dist-info/entry_points.txt
ptrender-0.0.3.dist-info/WHEEL
ptrender-0.0.3.dist-info/METADATA
ptrender-0.0.3.dist-info/RECORD
